hop_cli/__init__.py
hop_cli/__main__.py
hop_cli/bin/hop
hop_cli-0.2.2.dist-info/METADATA
hop_cli-0.2.2.dist-info/WHEEL
hop_cli-0.2.2.dist-info/entry_points.txt
hop_cli-0.2.2.dist-info/top_level.txt
hop_cli-0.2.2.dist-info/RECORD
